pg_transparent_alter_table/__init__.py
pg_transparent_alter_table/acl.py
pg_transparent_alter_table/data_copier.py
pg_transparent_alter_table/helper.py
pg_transparent_alter_table/main.py
pg_transparent_alter_table/pg_pool.py
pg_transparent_alter_table/tat.py
pg_transparent_alter_table/queries/apply_delta.plpgsql
pg_transparent_alter_table/queries/get_child_tables.sql
pg_transparent_alter_table/queries/get_table_info.sql
pg_transparent_alter_table/queries/store_delta.plpgsql
pg_transparent_alter_table-4.3.2.dist-info/licenses/AUTHORS
pg_transparent_alter_table-4.3.2.dist-info/licenses/LICENSE
pg_transparent_alter_table-4.3.2.dist-info/METADATA
pg_transparent_alter_table-4.3.2.dist-info/WHEEL
pg_transparent_alter_table-4.3.2.dist-info/entry_points.txt
pg_transparent_alter_table-4.3.2.dist-info/top_level.txt
pg_transparent_alter_table-4.3.2.dist-info/RECORD
